zope/proxy/__init__.py
zope/proxy/_zope_proxy_proxy.c
zope/proxy/_zope_proxy_proxy.cpython-311-x86_64-linux-gnu.so
zope/proxy/decorator.py
zope/proxy/interfaces.py
zope/proxy/proxy.h
zope/proxy/tests/__init__.py
zope/proxy/tests/test_compile_flags.py
zope/proxy/tests/test_decorator.py
zope/proxy/tests/test_proxy.py
zope_proxy-7.1.data/headers/proxy.h
zope_proxy-7.1.dist-info/METADATA
zope_proxy-7.1.dist-info/WHEEL
zope_proxy-7.1.dist-info/top_level.txt
zope_proxy-7.1.dist-info/RECORD
zope_proxy-7.1.dist-info/licenses/LICENSE.txt
