Metadata-Version: 2.4
Name: zope.proxy
Version: 7.1
Summary: Generic Transparent Proxies
Author-email: Zope Foundation and contributors <zope-dev@zope.dev>
Maintainer-email: Plone Foundation and contributors <zope-dev@zope.dev>
License-Expression: ZPL-2.1
Project-URL: Documentation, https://zopeproxy.readthedocs.io
Project-URL: Issues, https://github.com/zopefoundation/zope.proxy/issues
Project-URL: Source, https://github.com/zopefoundation/zope.proxy
Project-URL: Changelog, https://github.com/zopefoundation/zope.proxy/blob/master/CHANGES.rst
Keywords: zope,proxy,generic,transparent
Classifier: Development Status :: 5 - Production/Stable
Classifier: Framework :: Zope :: 3
Classifier: Intended Audience :: Developers
Classifier: Operating System :: OS Independent
Classifier: Programming Language :: Python
Classifier: Programming Language :: Python :: 3
Classifier: Programming Language :: Python :: 3 :: Only
Classifier: Programming Language :: Python :: 3.10
Classifier: Programming Language :: Python :: 3.11
Classifier: Programming Language :: Python :: 3.12
Classifier: Programming Language :: Python :: 3.13
Classifier: Programming Language :: Python :: 3.14
Classifier: Programming Language :: Python :: Implementation :: CPython
Classifier: Programming Language :: Python :: Implementation :: PyPy
Requires-Python: >=3.10
License-File: LICENSE.txt
Requires-Dist: zope.interface
Provides-Extra: docs
Requires-Dist: Sphinx; extra == "docs"
Requires-Dist: repoze.sphinx.autointerface; extra == "docs"
Requires-Dist: furo; extra == "docs"
Provides-Extra: test
Requires-Dist: zope.security>=7.3; extra == "test"
Requires-Dist: zope.testrunner>=6.4; extra == "test"
Dynamic: license-file
